<?xml version="1.0" encoding="UTF-8"?>
<!DOCTYPE mapper PUBLIC "-//mybatis.org//DTD Mapper 3.0//EN" "http://mybatis.org/dtd/mybatis-3-mapper.dtd">
<mapper namespace="com.lk.redo.dao.SysRedoMapper">
  <resultMap id="BaseResultMap" type="com.lk.redo.model.SysRedo">
    <!--
      WARNING - @mbg.generated
      This element is automatically generated by MyBatis Generator, do not modify.
      This element was generated on Fri Nov 23 15:31:51 CST 2018.
    -->
    <id column="id" jdbcType="BIGINT" property="id" />
    <result column="status" jdbcType="TINYINT" property="status" />
    <result column="biz_type" jdbcType="VARCHAR" property="bizType" />
    <result column="biz_invoke_clazz" jdbcType="VARCHAR" property="bizInvokeClazz" />
    <result column="biz_invoke_method" jdbcType="VARCHAR" property="bizInvokeMethod" />
    <result column="biz_invoke_method_argType" jdbcType="VARCHAR" property="bizInvokeMethodArgtype" />
    <result column="biz_invoke_args" jdbcType="VARCHAR" property="bizInvokeArgs" />
    <result column="fail_message" jdbcType="VARCHAR" property="failMessage" />
    <result column="redo_handler" jdbcType="VARCHAR" property="redoHandler" />
    <result column="auto_redo_able" jdbcType="BIT" property="autoRedoAble" />
    <result column="auto_redo_limit" jdbcType="INTEGER" property="autoRedoLimit" />
    <result column="auto_redo_count" jdbcType="INTEGER" property="autoRedoCount" />
    <result column="create_time" jdbcType="TIMESTAMP" property="createTime" />
    <result column="creator" jdbcType="VARCHAR" property="creator" />
    <result column="update_time" jdbcType="TIMESTAMP" property="updateTime" />
    <result column="updator" jdbcType="VARCHAR" property="updator" />
  </resultMap>
  <sql id="Base_Column_List">
    <!--
      WARNING - @mbg.generated
      This element is automatically generated by MyBatis Generator, do not modify.
      This element was generated on Fri Nov 23 15:31:51 CST 2018.
    -->
    id, status, biz_type, biz_invoke_clazz, biz_invoke_method, biz_invoke_method_argType, 
    biz_invoke_args, fail_message, redo_handler, auto_redo_able, auto_redo_limit, auto_redo_count, 
    create_time, creator, update_time, updator
  </sql>
  <select id="selectByPrimaryKey" parameterType="java.lang.Long" resultMap="BaseResultMap">
    <!--
      WARNING - @mbg.generated
      This element is automatically generated by MyBatis Generator, do not modify.
      This element was generated on Fri Nov 23 15:31:51 CST 2018.
    -->
    select 
    <include refid="Base_Column_List" />
    from sys_redo
    where id = #{id,jdbcType=BIGINT}
  </select>
  <delete id="deleteByPrimaryKey" parameterType="java.lang.Long">
    <!--
      WARNING - @mbg.generated
      This element is automatically generated by MyBatis Generator, do not modify.
      This element was generated on Fri Nov 23 15:31:51 CST 2018.
    -->
    delete from sys_redo
    where id = #{id,jdbcType=BIGINT}
  </delete>
  <insert id="insert" parameterType="com.lk.redo.model.SysRedo">
    <!--
      WARNING - @mbg.generated
      This element is automatically generated by MyBatis Generator, do not modify.
      This element was generated on Fri Nov 23 15:31:51 CST 2018.
    -->
    insert into sys_redo (id, status, biz_type, 
      biz_invoke_clazz, biz_invoke_method, biz_invoke_method_argType, 
      biz_invoke_args, fail_message, redo_handler, 
      auto_redo_able, auto_redo_limit, auto_redo_count, 
      create_time, creator, update_time, 
      updator)
    values (#{id,jdbcType=BIGINT}, #{status,jdbcType=TINYINT}, #{bizType,jdbcType=VARCHAR}, 
      #{bizInvokeClazz,jdbcType=VARCHAR}, #{bizInvokeMethod,jdbcType=VARCHAR}, #{bizInvokeMethodArgtype,jdbcType=VARCHAR}, 
      #{bizInvokeArgs,jdbcType=VARCHAR}, #{failMessage,jdbcType=VARCHAR}, #{redoHandler,jdbcType=VARCHAR}, 
      #{autoRedoAble,jdbcType=BIT}, #{autoRedoLimit,jdbcType=INTEGER}, #{autoRedoCount,jdbcType=INTEGER}, 
      #{createTime,jdbcType=TIMESTAMP}, #{creator,jdbcType=VARCHAR}, #{updateTime,jdbcType=TIMESTAMP}, 
      #{updator,jdbcType=VARCHAR})
  </insert>
  <insert id="insertSelective" parameterType="com.lk.redo.model.SysRedo">
    <!--
      WARNING - @mbg.generated
      This element is automatically generated by MyBatis Generator, do not modify.
      This element was generated on Fri Nov 23 15:31:51 CST 2018.
    -->
    insert into sys_redo
    <trim prefix="(" suffix=")" suffixOverrides=",">
      <if test="id != null">
        id,
      </if>
      <if test="status != null">
        status,
      </if>
      <if test="bizType != null">
        biz_type,
      </if>
      <if test="bizInvokeClazz != null">
        biz_invoke_clazz,
      </if>
      <if test="bizInvokeMethod != null">
        biz_invoke_method,
      </if>
      <if test="bizInvokeMethodArgtype != null">
        biz_invoke_method_argType,
      </if>
      <if test="bizInvokeArgs != null">
        biz_invoke_args,
      </if>
      <if test="failMessage != null">
        fail_message,
      </if>
      <if test="redoHandler != null">
        redo_handler,
      </if>
      <if test="autoRedoAble != null">
        auto_redo_able,
      </if>
      <if test="autoRedoLimit != null">
        auto_redo_limit,
      </if>
      <if test="autoRedoCount != null">
        auto_redo_count,
      </if>
      <if test="createTime != null">
        create_time,
      </if>
      <if test="creator != null">
        creator,
      </if>
      <if test="updateTime != null">
        update_time,
      </if>
      <if test="updator != null">
        updator,
      </if>
    </trim>
    <trim prefix="values (" suffix=")" suffixOverrides=",">
      <if test="id != null">
        #{id,jdbcType=BIGINT},
      </if>
      <if test="status != null">
        #{status,jdbcType=TINYINT},
      </if>
      <if test="bizType != null">
        #{bizType,jdbcType=VARCHAR},
      </if>
      <if test="bizInvokeClazz != null">
        #{bizInvokeClazz,jdbcType=VARCHAR},
      </if>
      <if test="bizInvokeMethod != null">
        #{bizInvokeMethod,jdbcType=VARCHAR},
      </if>
      <if test="bizInvokeMethodArgtype != null">
        #{bizInvokeMethodArgtype,jdbcType=VARCHAR},
      </if>
      <if test="bizInvokeArgs != null">
        #{bizInvokeArgs,jdbcType=VARCHAR},
      </if>
      <if test="failMessage != null">
        #{failMessage,jdbcType=VARCHAR},
      </if>
      <if test="redoHandler != null">
        #{redoHandler,jdbcType=VARCHAR},
      </if>
      <if test="autoRedoAble != null">
        #{autoRedoAble,jdbcType=BIT},
      </if>
      <if test="autoRedoLimit != null">
        #{autoRedoLimit,jdbcType=INTEGER},
      </if>
      <if test="autoRedoCount != null">
        #{autoRedoCount,jdbcType=INTEGER},
      </if>
      <if test="createTime != null">
        #{createTime,jdbcType=TIMESTAMP},
      </if>
      <if test="creator != null">
        #{creator,jdbcType=VARCHAR},
      </if>
      <if test="updateTime != null">
        #{updateTime,jdbcType=TIMESTAMP},
      </if>
      <if test="updator != null">
        #{updator,jdbcType=VARCHAR},
      </if>
    </trim>
  </insert>
  <update id="updateByPrimaryKeySelective" parameterType="com.lk.redo.model.SysRedo">
    <!--
      WARNING - @mbg.generated
      This element is automatically generated by MyBatis Generator, do not modify.
      This element was generated on Fri Nov 23 15:31:51 CST 2018.
    -->
    update sys_redo
    <set>
      <if test="status != null">
        status = #{status,jdbcType=TINYINT},
      </if>
      <if test="bizType != null">
        biz_type = #{bizType,jdbcType=VARCHAR},
      </if>
      <if test="bizInvokeClazz != null">
        biz_invoke_clazz = #{bizInvokeClazz,jdbcType=VARCHAR},
      </if>
      <if test="bizInvokeMethod != null">
        biz_invoke_method = #{bizInvokeMethod,jdbcType=VARCHAR},
      </if>
      <if test="bizInvokeMethodArgtype != null">
        biz_invoke_method_argType = #{bizInvokeMethodArgtype,jdbcType=VARCHAR},
      </if>
      <if test="bizInvokeArgs != null">
        biz_invoke_args = #{bizInvokeArgs,jdbcType=VARCHAR},
      </if>
      <if test="failMessage != null">
        fail_message = #{failMessage,jdbcType=VARCHAR},
      </if>
      <if test="redoHandler != null">
        redo_handler = #{redoHandler,jdbcType=VARCHAR},
      </if>
      <if test="autoRedoAble != null">
        auto_redo_able = #{autoRedoAble,jdbcType=BIT},
      </if>
      <if test="autoRedoLimit != null">
        auto_redo_limit = #{autoRedoLimit,jdbcType=INTEGER},
      </if>
      <if test="autoRedoCount != null">
        auto_redo_count = #{autoRedoCount,jdbcType=INTEGER},
      </if>
      <if test="createTime != null">
        create_time = #{createTime,jdbcType=TIMESTAMP},
      </if>
      <if test="creator != null">
        creator = #{creator,jdbcType=VARCHAR},
      </if>
      <if test="updateTime != null">
        update_time = #{updateTime,jdbcType=TIMESTAMP},
      </if>
      <if test="updator != null">
        updator = #{updator,jdbcType=VARCHAR},
      </if>
    </set>
    where id = #{id,jdbcType=BIGINT}
  </update>
  <update id="updateByPrimaryKey" parameterType="com.lk.redo.model.SysRedo">
    <!--
      WARNING - @mbg.generated
      This element is automatically generated by MyBatis Generator, do not modify.
      This element was generated on Fri Nov 23 15:31:51 CST 2018.
    -->
    update sys_redo
    set status = #{status,jdbcType=TINYINT},
      biz_type = #{bizType,jdbcType=VARCHAR},
      biz_invoke_clazz = #{bizInvokeClazz,jdbcType=VARCHAR},
      biz_invoke_method = #{bizInvokeMethod,jdbcType=VARCHAR},
      biz_invoke_method_argType = #{bizInvokeMethodArgtype,jdbcType=VARCHAR},
      biz_invoke_args = #{bizInvokeArgs,jdbcType=VARCHAR},
      fail_message = #{failMessage,jdbcType=VARCHAR},
      redo_handler = #{redoHandler,jdbcType=VARCHAR},
      auto_redo_able = #{autoRedoAble,jdbcType=BIT},
      auto_redo_limit = #{autoRedoLimit,jdbcType=INTEGER},
      auto_redo_count = #{autoRedoCount,jdbcType=INTEGER},
      create_time = #{createTime,jdbcType=TIMESTAMP},
      creator = #{creator,jdbcType=VARCHAR},
      update_time = #{updateTime,jdbcType=TIMESTAMP},
      updator = #{updator,jdbcType=VARCHAR}
    where id = #{id,jdbcType=BIGINT}
  </update>

  <select id="findAutoRedoItem" resultType="com.lk.redo.model.SysRedo">
    select
    <include refid="Base_Column_List" />
    from sys_redo
    where status = 0
    and auto_redo_able = true
    limit 10
  </select>

  <select id="countNeedRedoItem" resultType="java.lang.Integer">
    <![CDATA[
    select count(1)
    from sys_redo
    where (status = 2 or (status =0 and auto_redo_able = false )) and create_time >= DATE_SUB(NOW(), INTERVAL 10 MINUTE)
    ]]>
  </select>
</mapper>